nonebot_plugin_saalc-0.1.1.dist-info/METADATA
nonebot_plugin_saalc-0.1.1.dist-info/WHEEL
nonebot_plugin_saalc-0.1.1.dist-info/licenses/LICENSE
nonebot_plugin_saalc/__init__.py
nonebot_plugin_saalc/config.py
nonebot_plugin_saalc/message.py
nonebot_plugin_saalc-0.1.1.dist-info/RECORD
