Metadata-Version: 2.1
Name: nonebot-plugin-saalc
Version: 0.1.1
Summary: SAA 风格的 alc 兼容插件
Author-Email: Azide <rukuy@qq.com>
License: MIT
Requires-Python: >=3.9
Requires-Dist: nonebot2>=2.3.1
Requires-Dist: nonebot-plugin-alconna>=0.46.4
Requires-Dist: nonebot-plugin-send-anything-anywhere>=0.6.1
Requires-Dist: nonebot-adapter-onebot>=2.4.3; extra == "test"
Requires-Dist: pytest>=8.2.2; extra == "test"
Requires-Dist: pytest-asyncio>=0.23.7; extra == "test"
Requires-Dist: pytest-cov>=5.0.0; extra == "test"
Requires-Dist: nonebug>=0.3.7; extra == "test"
Requires-Dist: pytest-xdist>=3.6.1; extra == "test"
Provides-Extra: test
